{
  "slug": "rise-of-avalon-patch-14",
  "game_update": "Rise of Avalon",
  "patch_name": "Rise of Avalon Patch 14",
  "version": "1.17.410",
  "revision": "185092",
  "date": "10 February 2021",
  "date_iso": "2021-02-10",
  "description": "Rise of Avalon Patch 14 (10 February 2021) — Barbarian Bundle Now Available, Crystal League Changes, Combat Balance Changes, Fixes.",
  "keywords": [],
  "source_url": "https://forum.albiononline.com/index.php/Thread/144335-10-February-2021-Rise-of-Avalon-Patch-14/",
  "sections": [
    {
      "heading": "Barbarian Bundle Now Available",
      "description": null,
      "items": [],
      "subsections": [],
      "searchable_text": "Barbarian Bundle Now Available"
    },
    {
      "heading": "Crystal League Changes",
      "description": null,
      "items": [
        {
          "text": "Level 1 and 2 20v20 Crystal League matches now happen 6 times a day at the following times",
          "subitems": [
            {
              "text": "01:00:00 UTC"
            },
            {
              "text": "01:30:00 UTC"
            },
            {
              "text": "12:00:00 UTC"
            },
            {
              "text": "12:30:00 UTC"
            },
            {
              "text": "19:00:00 UTC"
            },
            {
              "text": "19:30:00 UTC"
            }
          ]
        },
        {
          "text": "All Crystal League no-shows for both 5v5 and 20v20 matches will still reward Season Points regardless of match level"
        }
      ],
      "subsections": [],
      "searchable_text": "Crystal League Changes Level 1 and 2 20v20 Crystal League matches now happen 6 times a day at the following times 01:00:00 UTC 01:30:00 UTC 12:00:00 UTC 12:30:00 UTC 19:00:00 UTC 19:30:00 UTC All Crystal League no-shows for both 5v5 and 20v20 matches will still reward Season Points regardless of match level"
    },
    {
      "heading": "Combat Balance Changes",
      "description": null,
      "items": [
        {
          "text": "Emergency Shield (Guardian Helmet)",
          "subitems": [
            {
              "text": "Cooldown: 30s → 40s",
              "stats": [
                {
                  "name": "Cooldown",
                  "from": "30s",
                  "to": "40s"
                }
              ]
            }
          ]
        }
      ],
      "subsections": [],
      "searchable_text": "Combat Balance Changes Emergency Shield (Guardian Helmet) Cooldown: 30s → 40s"
    },
    {
      "heading": "Fixes",
      "description": null,
      "items": [
        {
          "text": "Cooldown Reduction effect for Razor Cut (Bear Paws) now works as intended"
        },
        {
          "text": "Circle of Life (Nature Staff) now roots mounted targets as intended when cast with sufficient Thorns stacks"
        },
        {
          "text": "Emergency Shield (Guardian Helmet) can now be purged as intended"
        },
        {
          "text": "Additional minor graphical, terrain, and localization fixes"
        }
      ],
      "subsections": [],
      "searchable_text": "Fixes Cooldown Reduction effect for Razor Cut (Bear Paws) now works as intended Circle of Life (Nature Staff) now roots mounted targets as intended when cast with sufficient Thorns stacks Emergency Shield (Guardian Helmet) can now be purged as intended Additional minor graphical, terrain, and localization fixes"
    }
  ]
}